[
  
  {
    "id": "q2",
    "type": "reading",
    "passage": "The cat sat on the mat. It was a very happy cat...",
    "question": "Where did the cat sit?",
    "options": ["On the chair", "On the mat"],
    "answer": "On the mat"
  },
  {
    "id": "q3",
    "type": "matching",
    "pairs": [
      { "left": "Apple", "right": "Red" },
      { "left": "Banana", "right": "Yellow" }
    ]
  },
  [
  {
    "id": "q1",
    "type": "mcq",
    "question": "What is the capital of England?",
    "options": ["Paris", "London", "Berlin", "Madrid"],
    "answer": "London",
    "feedback": {
      "en": "Incorrect. London is the capital. Paris is in France.",
      "ar": "خطأ. لندن هي العاصمة. باريس في فرنسا."
    }
  },
  {
    "id": "q4",
    "type": "fill-blank",
    "text": "The sun rises in the ____.",
    "answer": "east",
    "feedback": {
      "en": "Try again! The sun always rises in the east.",
      "ar": "حاول مرة أخرى! تشرق الشمس دائماً من الشرق."
    }
  }
]
]